[{"key":"images","valType":"[Image]","defaultVal":["http://placehold.it/500x500","http://placehold.it/720x480","http://placehold.it/480x480"],"example":["http://placehold.it/500x500","http://placehold.it/720x480","http://placehold.it/480x480"],"options":[]},{"key":"petId","fieldLabel":"Pet ID","valType":"String","description":"Internal unique identifier.","defaultVal":"Auto generated","required":true,"example":"123456789","note":"","options":[]},{"key":"intakeDate","fieldLabel":"Intake Date?","valType":"Date","description":"","defaultVal":null,"required":true,"example":"2/17/2016","note":"","options":[]},{"key":"adoptable","fieldLabel":"Available for adoption at this time?","valType":"Boolean","description":"It the dog is available for adoption at this time.","defaultVal":false,"required":true,"example":false,"note":"","options":[true,false]},{"key":"lost","fieldLabel":"Possibly a lost or stray dog?","valType":"Boolean","description":"","defaultVal":false,"required":true,"example":false,"note":"","options":[true,false]},{"key":"lostGeoLat","fieldLabel":"If lost, approximate latitude where pet was found?","valType":"Location","description":"","defaultVal":"28.931905","required":false,"example":"28.931905","note":"new","options":[]},{"key":"lostGeoLon","fieldLabel":"If lost, approximate longitude where pet was found?","valType":"Location","description":"","defaultVal":"-81.9296189","required":false,"example":"-81.9296189","note":"new","options":[]},{"key":"species","fieldLabel":"Species","valType":"String","description":"Is the animal a bird, cat, dog, etc.?","defaultVal":"","required":true,"example":"Dog","note":"","options":[]},{"key":"purebred","fieldLabel":"Purebred?","valType":"Boolean","description":"Is the animal bred from parents of the same breed?","defaultVal":false,"required":false,"example":false,"note":"","options":[true,false]},{"key":"primaryBreed","fieldLabel":"Breed if purebred or primary breed if not?","valType":"String","description":"","defaultVal":"","required":false,"example":"Hound (Unknown Type)","note":"","options":["Affenpinscher","Afghan Hound","Airedale Terrier","Akbash","Akita","Alaskan Malamute","American Bulldog","American Eskimo Dog","American Hairless Terrier","American Pit Bull Terrier","American Staffordshire Terrier","American Water Spaniel","Anatolian Shepherd","Australian Cattle Dog","Australian Kelpie","Australian Shepherd","Australian Terrier","Basenji","Basset Griffon Vendeen","Basset Hound","Beagle","Bearded Collie","Beauceron","Bedlington Terrier","Belgian Laekenois","Belgian Malinois","Belgian Shepherd","Belgian Tervuren","Bernese Mountain Dog","Bichon Frise","Black Mouth Cur","Black and Tan Coonhound","Bloodhound","Blue Heeler","Blue Lacy/Texas Lacy","Bluetick Coonhound","Bobtail","Bolognese","Border Collie","Border Terrier","Borzoi","Boston Terrier","Bouvier des Flandres","Boxer","Boykin Spaniel","Briard","Brittany","Brussels Griffon","Bull Terrier","Bulldog","Bullmastiff","Cairn Terrier","Canaan Dog","Canary Dog","Cane Corso","Cardigan Welsh Corgi","Carolina Dog","Catahoula Leopard Dog","Cattle Dog","Cavalier King Charles Spaniel","Chesapeake Bay Retriever","Chihuahua","Chinese Crested","Chow Chow","Clumber Spaniel","Cockapoo","Cocker Spaniel","Collie","Coonhound","Coonhound (Unknown Type)","Corgi","Coton de Tulear","Curly-Coated Retriever","Dachshund","Dalmatian","Dandie Dinmont Terrier","Deerhound","Doberman Pinscher","Dogo Argentino","Dogue de Bordeaux","Dutch Shepherd","English (Redtick) Coonhound","English Bulldog","English Mastiff","English Pointer","English Setter","English Sheepdog","English Shepherd","English Springer Spaniel","English Toy Spaniel","Entlebucher","Eskimo Dog","Eskimo Spitz","Feist","Field Spaniel","Fila Brasileiro","Finnish Lapphund","Finnish Spitz","Flat-Coated Retriever","Fox Terrier (Smooth)","Fox Terrier (Toy)","Fox Terrier (Wirehaired)","Foxhound","French Bulldog","French Mastiff","German Pinscher","German Shepherd Dog","German Shorthaired Pointer","German Wirehaired Pointer","Giant Schnauzer","Glen of Imaal Terrier","Golden Retriever","Goldendoodle","Gordon Setter","Great Dane","Great Pyrenees","Greater Swiss Mountain Dog","Greyhound","Halden Hound (Haldenstrover)","Harrier","Havanese","Hound (Unknown Type)","Hovawart","Hungarian Puli","Hungarian Water Dog","Husky","Ibizan Hound","Irish Setter","Irish Terrier","Irish Water Spaniel","Irish Wolfhound","Italian Greyhound","Italian Spinone","Jack Russell Terrier","Japanese Chin","Jindo","Kai Dog","Karelian Bear Dog","Keeshond","Kerry Blue Terrier","King Charles Spaniel","Kishu","Komondor","Kuvasz","Kyi Leo","Labradoodle","Labrador Retriever","Lakeland Terrier","Lancashire Heeler","Leonberger","Lhasa Apso","Löwchen","Maltese","Manchester Terrier","Maremma Sheepdog","Mastiff","Mexican Hairless","Miniature Pinscher","Miniature Poodle","Miniature Schnauzer","Mountain Cur","Munsterlander","Neapolitan Mastiff","Newfoundland","Norfolk Terrier","Norwegian Buhund","Norwegian Elkhound","Norwich Terrier","Nova Scotia Duck-Tolling Retriever","Old English Sheepdog","Otterhound","Papillon","Parson Russell Terrier","Patterdale Terrier (Fell Terrier)","Pekingese","Pembroke Welsh Corgi","Petit Basset Griffon Vendeen","Pharaoh Hound","Pit Bull Terrier","Plott Hound","Podengo Portugueso","Pointer","Polish Lowland Sheepdog","Pomeranian","Poodle (Miniature)","Poodle (Standard)","Poodle (Toy or Tea Cup)","Portuguese Water Dog","Presa Canario","Pug","Puli","Pumi","Rat Terrier","Redbone Coonhound","Redtick Coonhound","Retriever (Unknown Type)","Rhodesian Ridgeback","Rottweiler","Russian Wolfhound","Saluki","Samoyed","Schiller Hound","Schipperke","Schnauzer (Giant)","Schnauzer (Miniature)","Schnauzer (Standard)","Scottie, Scottish Terrier","Scottish Deerhound","Sealyham Terrier","Setter (Unknown Type)","Shar Pei","Sheltie, Shetland Sheepdog","Shepherd (Unknown Type)","Shiba Inu","Shih Tzu","Siberian Husky","Silky Terrier","Skye Terrier","Sloughi","Smooth Fox Terrier","Spaniel (Unknown Type)","Spitz (Unknown Type, Large)","Spitz (Unknown Type, Medium)","Spitz (Unknown Type, Small)","Springer Spaniel","St. Bernard","Staffordshire Bull Terrier","Standard Poodle","Standard Schnauzer","Sussex Spaniel","Swedish Vallhund","Tea Cup Poodle","Terrier (Unknown Type, Medium)","Terrier (Unknown Type, Small)","Thai Ridgeback","Tibetan Mastiff","Tibetan Spaniel","Tibetan Terrier","Tosa Inu","Toy Fox Terrier","Toy Poodle","Treeing Walker Coonhound","Vizsla","Weimaraner","Welsh Corgi","Welsh Springer Spaniel","Welsh Terrier","Westie, West Highland White Terrier","Wheaten Terrier","Whippet","Wirehaired Fox Terrier","Wirehaired Pointing Griffon","Wolf Hybrid","Xoloitzcuintle/Mexican Hairless","Yorkie, Yorkshire Terrier"]},{"key":"secondaryBreed","fieldLabel":"Secondary breed if not purebred?","valType":"String","description":"","defaultVal":"","required":false,"example":"Terrier (Unknown Type, Medium)","note":"","options":["Affenpinscher","Afghan Hound","Airedale Terrier","Akbash","Akita","Alaskan Malamute","American Bulldog","American Eskimo Dog","American Hairless Terrier","American Pit Bull Terrier","American Staffordshire Terrier","American Water Spaniel","Anatolian Shepherd","Australian Cattle Dog","Australian Kelpie","Australian Shepherd","Australian Terrier","Basenji","Basset Griffon Vendeen","Basset Hound","Beagle","Bearded Collie","Beauceron","Bedlington Terrier","Belgian Laekenois","Belgian Malinois","Belgian Shepherd","Belgian Tervuren","Bernese Mountain Dog","Bichon Frise","Black Mouth Cur","Black and Tan Coonhound","Bloodhound","Blue Heeler","Blue Lacy/Texas Lacy","Bluetick Coonhound","Bobtail","Bolognese","Border Collie","Border Terrier","Borzoi","Boston Terrier","Bouvier des Flandres","Boxer","Boykin Spaniel","Briard","Brittany","Brussels Griffon","Bull Terrier","Bulldog","Bullmastiff","Cairn Terrier","Canaan Dog","Canary Dog","Cane Corso","Cardigan Welsh Corgi","Carolina Dog","Catahoula Leopard Dog","Cattle Dog","Cavalier King Charles Spaniel","Chesapeake Bay Retriever","Chihuahua","Chinese Crested","Chow Chow","Clumber Spaniel","Cockapoo","Cocker Spaniel","Collie","Coonhound","Coonhound (Unknown Type)","Corgi","Coton de Tulear","Curly-Coated Retriever","Dachshund","Dalmatian","Dandie Dinmont Terrier","Deerhound","Doberman Pinscher","Dogo Argentino","Dogue de Bordeaux","Dutch Shepherd","English (Redtick) Coonhound","English Bulldog","English Mastiff","English Pointer","English Setter","English Sheepdog","English Shepherd","English Springer Spaniel","English Toy Spaniel","Entlebucher","Eskimo Dog","Eskimo Spitz","Feist","Field Spaniel","Fila Brasileiro","Finnish Lapphund","Finnish Spitz","Flat-Coated Retriever","Fox Terrier (Smooth)","Fox Terrier (Toy)","Fox Terrier (Wirehaired)","Foxhound","French Bulldog","French Mastiff","German Pinscher","German Shepherd Dog","German Shorthaired Pointer","German Wirehaired Pointer","Giant Schnauzer","Glen of Imaal Terrier","Golden Retriever","Goldendoodle","Gordon Setter","Great Dane","Great Pyrenees","Greater Swiss Mountain Dog","Greyhound","Halden Hound (Haldenstrover)","Harrier","Havanese","Hound (Unknown Type)","Hovawart","Hungarian Puli","Hungarian Water Dog","Husky","Ibizan Hound","Irish Setter","Irish Terrier","Irish Water Spaniel","Irish Wolfhound","Italian Greyhound","Italian Spinone","Jack Russell Terrier","Japanese Chin","Jindo","Kai Dog","Karelian Bear Dog","Keeshond","Kerry Blue Terrier","King Charles Spaniel","Kishu","Komondor","Kuvasz","Kyi Leo","Labradoodle","Labrador Retriever","Lakeland Terrier","Lancashire Heeler","Leonberger","Lhasa Apso","Löwchen","Maltese","Manchester Terrier","Maremma Sheepdog","Mastiff","Mexican Hairless","Miniature Pinscher","Miniature Poodle","Miniature Schnauzer","Mountain Cur","Munsterlander","Neapolitan Mastiff","Newfoundland","Norfolk Terrier","Norwegian Buhund","Norwegian Elkhound","Norwich Terrier","Nova Scotia Duck-Tolling Retriever","Old English Sheepdog","Otterhound","Papillon","Parson Russell Terrier","Patterdale Terrier (Fell Terrier)","Pekingese","Pembroke Welsh Corgi","Petit Basset Griffon Vendeen","Pharaoh Hound","Pit Bull Terrier","Plott Hound","Podengo Portugueso","Pointer","Polish Lowland Sheepdog","Pomeranian","Poodle (Miniature)","Poodle (Standard)","Poodle (Toy or Tea Cup)","Portuguese Water Dog","Presa Canario","Pug","Puli","Pumi","Rat Terrier","Redbone Coonhound","Redtick Coonhound","Retriever (Unknown Type)","Rhodesian Ridgeback","Rottweiler","Russian Wolfhound","Saluki","Samoyed","Schiller Hound","Schipperke","Schnauzer (Giant)","Schnauzer (Miniature)","Schnauzer (Standard)","Scottie, Scottish Terrier","Scottish Deerhound","Sealyham Terrier","Setter (Unknown Type)","Shar Pei","Sheltie, Shetland Sheepdog","Shepherd (Unknown Type)","Shiba Inu","Shih Tzu","Siberian Husky","Silky Terrier","Skye Terrier","Sloughi","Smooth Fox Terrier","Spaniel (Unknown Type)","Spitz (Unknown Type, Large)","Spitz (Unknown Type, Medium)","Spitz (Unknown Type, Small)","Springer Spaniel","St. Bernard","Staffordshire Bull Terrier","Standard Poodle","Standard Schnauzer","Sussex Spaniel","Swedish Vallhund","Tea Cup Poodle","Terrier (Unknown Type, Medium)","Terrier (Unknown Type, Small)","Thai Ridgeback","Tibetan Mastiff","Tibetan Spaniel","Tibetan Terrier","Tosa Inu","Toy Fox Terrier","Toy Poodle","Treeing Walker Coonhound","Vizsla","Weimaraner","Welsh Corgi","Welsh Springer Spaniel","Welsh Terrier","Westie, West Highland White Terrier","Wheaten Terrier","Whippet","Wirehaired Fox Terrier","Wirehaired Pointing Griffon","Wolf Hybrid","Xoloitzcuintle/Mexican Hairless","Yorkie, Yorkshire Terrier"]},{"key":"sex","fieldLabel":"Sex?","valType":"String","description":"","defaultVal":"","required":false,"example":"Female","note":"","options":["Male","Female"]},{"key":"spayedNeutered","fieldLabel":"Spayed or neutered?","valType":"Boolean","description":"","defaultVal":false,"required":false,"example":true,"note":"","options":[true,false]},{"key":"age","fieldLabel":"Age","valType":"String","description":"","defaultVal":"","required":false,"example":"1-2 years","note":"","options":["0-6 months","6-12 months","1-2 years","2-4 years","4-7 years","7-10 years","10+ years"]},{"key":"color","fieldLabel":"Color","valType":"String","description":"","defaultVal":"","required":false,"example":"White with Tan, Yellow or Fawn","note":"","options":["Black","Black with Brown, Red, Golden, Orange or Chestnut","Black with Fawn, Tan or Yellow","Black with Gray or Silver","Black with White","Blue, Gray, Salt & Pepper or Silver","Blue, Gray, Salt & Pepper or Silver Merle","Blue, Gray, Salt & Pepper or Silver with Black","Blue, Gray, Salt & Pepper or Silver with White","Brindle","Brindle with White","Brown or Chocolate","Brown or Chocolate with Black","Brown or Chocolate with Tan","Brown or Chocolate with White","Chestnut, Golden, Orange or Red","Chestnut, Golden, Orange or Red Merle","Chestnut, Golden, Orange or Red with Black","Chestnut, Golden, Orange or Red with White","Fawn, Tan or Yellow","Fawn, Tan or Yellow with Black","Fawn, Tan or Yellow with White","Tricolor (Black, Brown and White)","White","White with Black","White with Brown or Chocolate","White with Gray, Blue, Silver, Salt & Pepper","White with Red, Golden, Orange or Chestnut","White with Tan, Yellow or Fawn"]},{"key":"hairLength","fieldLabel":"Hair Length","valType":"String","description":"","defaultVal":"","required":false,"example":"Short","note":"","options":["Short","Medium","Long"]},{"key":"size","fieldLabel":"Size?","valType":"String","description":"","defaultVal":"","required":false,"example":"Medium (26-45 lbs.)","note":"","options":["Toy (0-10 lbs.)","Small (11-25 lbs.)","Medium (26-45 lbs.)","Large (46-70 lbs.)","Extra Large (71-90 lbs.)","Giant (91+ lbs.)"]},{"key":"microchip","fieldLabel":"Microchiped?","valType":"String","description":"Is the dog microchiped?","defaultVal":"Unknown","required":false,"example":"No","note":"updated_type","options":["Yes","No","Unknown"]},{"key":"microchip_number","fieldLabel":"Microchip number?","valType":"String","description":"If the dog is microchiped, what is the number?","defaultVal":"","required":false,"example":"","note":"new","options":[]},{"key":"caseActive","fieldLabel":"Case active?","valType":"Boolean","description":"Is this an active case or has the dog be adopted?","defaultVal":true,"required":true,"example":true,"note":"new","options":[true,false]},{"key":"caseNumber","fieldLabel":"Case number?","valType":"String","description":"Lake County Sheriff's Office CAD number.","defaultVal":"","required":false,"example":"L16004567","note":"new","options":[]},{"key":"activityLevel","fieldLabel":"Activity level?","valType":"String","description":"What is the dog's activity level?","defaultVal":"","required":false,"example":"Medium","note":"","options":["High","Medium","Low"]},{"key":"actQuickly","fieldLabel":"Important to adopt soon?","valType":"Boolean","description":"If it is important to adopt this dog soon.","defaultVal":false,"required":false,"example":false,"note":"","options":[true,false]},{"key":"crateTrained","fieldLabel":"Crate Trained","valType":"String","description":"","defaultVal":"Unknown","required":false,"example":"Yes","note":"updated_type","options":["Yes","No","Unknown"]},{"key":"currentHeartwormTest","fieldLabel":"Heartworm test current?","valType":"String","description":"","defaultVal":"Unknown","required":false,"example":"Yes","note":"updated_type","options":["Tested Positive","Tested Negative","No","Unknown"]},{"key":"currentShots","fieldLabel":"All shots current?","valType":"String","description":"","defaultVal":"Unknown","required":false,"example":"Yes","note":"updated_type","options":["Yes","No","Unknown"]},{"key":"description","fieldLabel":"Description","valType":"String","description":"Brief narrative and call to action.","defaultVal":"","required":false,"example":"This is Odie. Odie is a 1 year old, neutered male, Hound Terrier mix. He loves to run and play with other dogs and he also enjoys snuggling up and getting his belly rubbed. He has a wire coat and he is crate trained too. He is only 26 lbs. If you have been looking for a dog that is not too big and not too little, Odie might just be the right one for you! If you would like to meet Odie, Please contact your local Lady Lake AnimalDocuments Control at 352-751-1530.","note":"What is the appropriate text length constraint for this field?","options":[]},{"key":"goodWithCats","fieldLabel":"Good with other cats?","valType":"String","description":"","defaultVal":"Unknown","required":false,"example":"","note":"updated_type","options":["Yes","No","Unknown"]},{"key":"goodWithDogs","fieldLabel":"Good with other dogs?","valType":"String","description":"","defaultVal":"Unknown","required":false,"example":"","note":"updated_type","options":["Yes","No","Unknown"]},{"key":"goodWithKids","fieldLabel":"Good with children?","valType":"String","description":"","defaultVal":"Unknown","required":false,"example":"","note":"updated_type","options":["Yes","No","Unknown"]},{"key":"houseTrained","fieldLabel":"House Trained","valType":"String","description":"","defaultVal":"Unknown","required":false,"example":"","note":"updated_type","options":["Yes","No","Unknown"]},{"key":"petName","fieldLabel":"Pet Name","valType":"String","description":"Friendly name of the dog.","defaultVal":"","required":false,"example":"Odie","note":"","options":[]},{"key":"specialNeeds","fieldLabel":"Special needs?","valType":"Boolean","description":"","defaultVal":false,"required":false,"example":false,"note":"","options":[true,false]},{"key":"shelterAddrCity","fieldLabel":"Shelter City","valType":"String","description":"","defaultVal":"Lady Lake","required":false,"example":"","note":"","options":[]},{"key":"shelterAddrLine1","fieldLabel":"Shelter Address Line 1","valType":"String","description":"","defaultVal":"132 Skyline Dr.","required":false,"example":"","note":"","options":[]},{"key":"shelterAddrLine2","fieldLabel":"Shelter Address Line 2","valType":"String","description":"","defaultVal":"","required":false,"example":"","note":"","options":[]},{"key":"shelterAddrSt","fieldLabel":"Shelter State","valType":"String","description":"","defaultVal":"FL","required":false,"example":"","note":"","options":[]},{"key":"shelterAddrZip","fieldLabel":"Shelter Zip","valType":"String","description":"","defaultVal":"32159","required":false,"example":"","note":"","options":[]},{"key":"shelterContact","fieldLabel":"Shelter Contact","valType":"String","description":"","defaultVal":"Denise Williams","required":false,"example":"","note":"","options":[]},{"key":"shelterEmail","fieldLabel":"Shelter Email","valType":"String","description":"","defaultVal":"aco@ladylake.org","required":false,"example":"","note":"","options":[]},{"key":"shelterGeoLat","fieldLabel":"Shelter Latitude","valType":"Location","description":"","defaultVal":"Location","required":false,"example":"","note":"new","options":[]},{"key":"shelterGeoLon","fieldLabel":"Shelter Longitude","valType":"Location","description":"","defaultVal":"Location","required":false,"example":"","note":"new","options":[]},{"key":"shelterId","fieldLabel":"Shelter ID","valType":"Number","description":"Adopt-a-Pet Shetler ID","defaultVal":"90778","required":false,"example":"","note":"","options":[]},{"key":"shelterName","fieldLabel":"Shelter Name","valType":"String","description":"","defaultVal":"Lady Lake AnimalDocuments Control","required":false,"example":"","note":"","options":[]},{"key":"shelterPhone","fieldLabel":"Shelter Phone","valType":"String","description":"","defaultVal":"352-751-1530","required":false,"example":"","note":"","options":[]},{"key":"shelterUrl","fieldLabel":"Shelter Website Address","valType":"String","description":"","defaultVal":"https://www.ladylake.org/police-department/animal-control-2","required":false,"example":"","note":"","options":[]}]